sreddit/__init__.py
sreddit/srtitles.py
sreddit-1.2.5.dist-info/LICENSE
sreddit-1.2.5.dist-info/METADATA
sreddit-1.2.5.dist-info/WHEEL
sreddit-1.2.5.dist-info/top_level.txt
sreddit-1.2.5.dist-info/RECORD
