Metadata-Version: 2.1
Name: sreddit
Version: 1.2.5
Summary: Web scraper for subreddits
Home-page: https://github.com/Mandy-cyber/SubRedditScraper
Author: MandyCyber
Author-email: 
License: UNKNOWN
Platform: UNKNOWN
Classifier: Programming Language :: Python :: 3
Classifier: License :: OSI Approved :: MIT License
Classifier: Operating System :: OS Independent
Requires-Python: >=3.6
License-File: LICENSE
Requires-Dist: selenium
Requires-Dist: time
Requires-Dist: get-chrome-driver
